aribot_cli/__init__.py
aribot_cli/cli.py
aribot_cli/sdk.py
aribot_cli/theme.py
aribot_cli-1.4.0.dist-info/METADATA
aribot_cli-1.4.0.dist-info/WHEEL
aribot_cli-1.4.0.dist-info/entry_points.txt
aribot_cli-1.4.0.dist-info/top_level.txt
aribot_cli-1.4.0.dist-info/RECORD
