Metadata-Version: 2.4
Name: aribot-cli
Version: 1.4.0
Summary: Aribot - Economic, Regulatory & Security APIs for Modern Applications. Advanced multi-framework threat modeling (STRIDE, PASTA, NIST, Aristiun), 100+ compliance standards, Cloud Security, FinOps, and Red Team automation.
Author-email: Ayurak AI <support@ayurak.com>
Maintainer-email: Ayurak AI <support@ayurak.com>
License: MIT
Project-URL: Homepage, https://aribot.ayurak.com
Project-URL: Documentation, https://developer.ayurak.com/docs
Project-URL: Repository, https://github.com/ayurak/aribot-cli
Project-URL: Issues, https://github.com/ayurak/aribot-cli/issues
Project-URL: Changelog, https://github.com/ayurak/aribot-cli/releases
Keywords: threat-modeling,security,stride,cspm,cnapp,cloud-security,devsecops,cli,ai,appsec,vulnerability,risk-assessment,compliance,soc2,iso27001,pci-dss,gdpr,hipaa,finops,red-team,attack-simulation
Classifier: Development Status :: 5 - Production/Stable
Classifier: Environment :: Console
Classifier: Intended Audience :: Developers
Classifier: Intended Audience :: Information Technology
Classifier: Intended Audience :: System Administrators
Classifier: License :: OSI Approved :: MIT License
Classifier: Operating System :: OS Independent
Classifier: Programming Language :: Python :: 3
Classifier: Programming Language :: Python :: 3.9
Classifier: Programming Language :: Python :: 3.10
Classifier: Programming Language :: Python :: 3.11
Classifier: Programming Language :: Python :: 3.12
Classifier: Topic :: Security
Classifier: Topic :: Software Development :: Quality Assurance
Classifier: Topic :: System :: Systems Administration
Requires-Python: >=3.9
Requires-Dist: click>=8.0.0
Requires-Dist: rich>=13.0.0
Requires-Dist: httpx>=0.25.0
Requires-Dist: keyring>=24.0.0
Requires-Dist: pydantic>=2.0.0
